{
  "avdc": {
    "version": "3.1.0",
    "type": "catalog"
  },
  "source": {
    "dataRepository": "Clayyper/DadosRep",
    "dataDefaultBranch": "main"
  },
  "index": {
    "indexRepository": "Clayyper/DadosRep",
    "indexDefaultBranch": "main"
  },
  "generatedAt": "2026-06-27T14:19:16.986Z",
  "files": [
    {
      "path": "avdc-notes/2026-06-27-scriptiniciarfedora-248d.vcd",
      "directory": "avdc-notes",
      "name": "2026-06-27-scriptiniciarfedora-248d.vcd",
      "extension": "vcd",
      "sizeBytes": 1171,
      "sha": "a9eb3f6957d8ed40e0db148b9bf91afaec4297dd",
      "githubUrl": "https://github.com/Clayyper/DadosRep/blob/main/avdc-notes/2026-06-27-scriptiniciarfedora-248d.vcd",
      "githubUpdatedAt": "2026-06-27T14:18:50Z",
      "discoveredAt": "2026-06-27T14:19:16.986Z",
      "displayDate": "2026-06-27T14:18:50Z",
      "contentIndexed": true,
      "contentPreview": "#!/data/data/com.termux/files/usr/bin/bash pkill -9 -f termux-x11 2>/dev/null pkill -9 -f pulseaudio 2>/dev/null if command -v pulseaudio >/dev/null 2>&1; then pulseaudio --start \\ --load=\"module-native-protocol-tcp auth-ip-acl=127.0.0.1 auth-anonymous=1\" \\ --exit-idle-time=-1 2>/dev/null fi export XDG_RUNTIME_DIR=\"$TMPDIR\" rm -rf \"$TMPDIR/.X11-unix\" termux-x11 :0 -ac & sleep 3 am start --user 0 -n com.termux.x11/com"
    }
  ]
}
